{
  "generated_at": "2026-02-09T19:05:41.834Z",
  "stage": "quant_signals",
  "old_model_id": "deterministic:quant-v1",
  "new_model_id": "deterministic:quant-v2-test",
  "dry_run": true,
  "notes": "dry run test",
  "dataset": {
    "path": "C:\\Users\\dusti\\AppData\\Local\\Temp\\promotion-flow-4XiobJ\\stage_quant.jsonl",
    "total_rows": 1,
    "eligible_rows": 1,
    "approved_only": true,
    "min_rows_required": 30,
    "forced": true,
    "sha256": "897dbe42c2ddcfecaf709727799173f470572bbdfe2dced383de001a50c161b0"
  },
  "evals": {
    "passed": true,
    "pipeline": {
      "totals": {
        "fixtures": 3,
        "passed": 3,
        "failed": 0
      },
      "report_path": "C:\\Users\\dusti\\git\\2ndmynd-workspace\\evals\\report_20260209T190540Z.json"
    },
    "stage": {
      "totals": {
        "fixtures": 3,
        "passed": 3,
        "failed": 0
      },
      "report_path": "C:\\Users\\dusti\\git\\2ndmynd-workspace\\evals\\report_20260209T190541Z.json"
    }
  }
}